atdf_easy/__init__.py
atdf_easy/atdf.py
atdf_easy/atdf_read_file.py
atdf_easy/atdf_records.py
atdf_easy/atdf_variables.py
atdf_easy-1.2.dist-info/METADATA
atdf_easy-1.2.dist-info/WHEEL
atdf_easy-1.2.dist-info/entry_points.txt
atdf_easy-1.2.dist-info/top_level.txt
atdf_easy-1.2.dist-info/RECORD
